fdtdcurrent/__init__.py
fdtdcurrent/conductor.py
fdtdcurrent/constants.py
fdtdcurrent/detector.py
fdtdcurrent/grid.py
fdtdcurrent/grid_object.py
fdtdcurrent/mylogging.py
fdtdcurrent/source.py
fdtdcurrent/typing_.py
fdtdcurrent/visualization/__init__.py
fdtdcurrent/visualization/matplotlib_helpers.py
fdtdcurrent-0.0.1.4.dist-info/METADATA
fdtdcurrent-0.0.1.4.dist-info/WHEEL
fdtdcurrent-0.0.1.4.dist-info/licenses/LICENSE
fdtdcurrent-0.0.1.4.dist-info/RECORD
